sketch/__init__.py
sketch/core.py
sketch/metrics.py
sketch/pandas_extension.py
sketch/references.py
sketch/sketches.py
sketch-0.5.2.dist-info/LICENSE
sketch-0.5.2.dist-info/METADATA
sketch-0.5.2.dist-info/WHEEL
sketch-0.5.2.dist-info/top_level.txt
sketch-0.5.2.dist-info/RECORD
