Metadata-Version: 2.1
Name: sketch
Version: 0.5.2
Summary: Compute, store and operate on data sketches
License: MIT License
Project-URL: homepage, https://github.com/approximatelabs/sketch
Keywords: data,sketch,model,etl,automatic,join,ai,embedding,profiling
Classifier: Programming Language :: Python :: 3
Requires-Python: >=3.8
License-File: LICENSE
Requires-Dist: pandas >=1.3.0
Requires-Dist: datasketch >=1.5.8
Requires-Dist: datasketches >=4.0.0
Requires-Dist: ipython
Requires-Dist: lambdaprompt >=0.6.1
Requires-Dist: packaging
Provides-Extra: all
Requires-Dist: sketch[local] ; extra == 'all'
Provides-Extra: local
Requires-Dist: lambdaprompt[local] ; extra == 'local'
